Workbook

Sheet README
B2: IDLE BANK TYCOON · GAME ECONOMY CASE STUDY
B3: A working economy model: (A) a soft-currency sink feature + (B) rewarded-ad reward tuning
B5: PURPOSE
B6: This workbook is a demonstration economy model built for the Game Economy Designer application (Idle Bank Tycoon team, Kolibri Games). It tackles two sourced opportunities in the live game and shows the full economy-design workflow: a master-parameter model, source/sink balancing, ROI and monetisation math, KPI impact, and a safe A/B test plan. All live values flow from the Parameters tab. Change one blue cell and the whole model rebalances.
B11: HOW TO USE THIS MODEL
B12: 1. | C12: Open the Parameters tab. Every BLUE cell is an input you can change. Everything else recalculates.
B13: 2. | C13: Baseline Economy shows the core-loop income curve and the late-game 'cash surplus' problem the feature solves.
B14: 3. | C14: Loan Desk (Option A) models a soft-currency sink that converts idle cash into a temporary income multiplier.
B15: 4. | C15: Ad Tuning (Option B) sizes the rewarded-video reward and estimates the ad-revenue / ARPDAU impact.
B16: 5. | C16: KPI Impact combines both levers into a retention + monetisation view, with a sensitivity table.
B18: COLOUR LEGEND
B19: Blue text | C19: Hardcoded input (change for scenarios)
B20: Black text | C20: Formula / calculation
B21: Green text | C21: Link to another tab
B22: Yellow fill | C22: Key assumption needing attention
B24: NOTE ON DATA: Kolibri does not publish per-level cost tables or live KPIs, so the core-loop numbers here are labelled ASSUMPTIONS, calibrated to public third-party estimates (AppQuantum/Sensor Tower, 2023) and standard idle-game math (Pecorella, GDC). The value of the model is the method and the reasoning. None of these are Kolibri's internal figures. See the Sources tab.

Sheet Parameters
A2: PARAMETERS · MASTER SOURCE OF TRUTH
A3: All BLUE cells are inputs. Every other tab links here. Change a value and the whole model re-balances.
A4: A. CORE LOOP (reconstructed baseline, illustrative)
B5: Parameter | C5: Value | D5: Unit | E5: Notes / rationale
B6: Starting income per second (Bank 1) | C6: 50 | D6: $/sec | E6: Early-game cash/sec at first prestige. Calibrated to onboarding feel.
B7: Income growth per player level | C7: 1.18 | D7: x / level | E7: Production multiplier per reputation level. Idle norm ~1.1–1.2x (Pecorella).
B8: Upgrade cost growth per level | C8: 1.21 | D8: x / level | E8: Exponential cost curve. Must exceed income growth so progress self-throttles.
B9: Base upgrade cost (Bank 1, level 1) | C9: 100 | D9: $ | E9: Anchor price for the first upgrade.
B10: Player levels modelled | C10: 60 | D10: levels | E10: Horizon for the baseline curve (covers ~first several banks).
B11: Avg sessions per day | C11: 4 | D11: sessions | E11: Casual idle norm (GameAnalytics 2024 ~4/day).
B12: Avg minutes per session | C12: 6 | D12: min | E12: Casual median 5–6 min.
B13: Offline earnings cap | C13: 12 | D13: hours | E13: IBT caps offline income at 12h (+30 min per manager).
A15: B. PLAYER BASE & SEGMENTATION
B16: Parameter | C16: Value | D16: Unit | E16: Notes / rationale
B17: Daily active users (DAU) modelled | C17: 200000 | D17: users | E17: Illustrative DAU for revenue scaling. Scale to taste.
B18: Payer conversion rate | C18: 0.0183 | D18: % | E18: Industry IAP conversion 1.83% (Unity 2024).
B19: Share of DAU who watch ads (opt-in) | C19: 0.55 | D19: % | E19: Ad-watcher share; idle audiences are highly ad-tolerant.
B20: Whale share of payers | C20: 0.05 | D20: % | E20: Top ~5% of players ≈ 48% of IAP revenue (Moloco 2025).
A22: C. AD ECONOMICS (Option B inputs)
B23: Parameter | C23: Value | D23: Unit | E23: Notes / rationale
B24: Rewarded video eCPM (blended) | C24: 15 | D24: $ / 1000 | E24: Rewarded eCPM; Tier-1 higher, blended global lower.
B25: Interstitial eCPM (blended) | C25: 8 | D25: $ / 1000 | E25: Interstitial blended eCPM.
B26: Current rewarded views per ad-watcher/day | C26: 6 | D26: views | E26: Baseline opt-in views/day per ad-watcher.
B27: Tuned rewarded views per ad-watcher/day | C27: 8.5 | D27: views | E27: Target after better reward sizing + placement.
B28: Ad completion rate | C28: 0.92 | D28: % | E28: Rewarded completion 85–95% when reward feels meaningful.
A30: D. LOAN DESK FEATURE (Option A inputs)
B31: Parameter | C31: Value | D31: Unit | E31: Notes / rationale
B32: Loan principal as % of cash balance | C32: 0.4 | D32: % | E32: Max share of idle cash a player can lock into a loan.
B33: Loan term (real-time) | C33: 4 | D33: hours | E33: How long cash is locked before repayment + reward.
B34: Income multiplier while loan active | C34: 1.5 | D34: x | E34: Temporary boost to income/sec while the loan runs. The 'interest' the player earns.
B35: Interest repaid to player (soft) | C35: 0.1 | D35: % | E35: Bonus cash returned on top of principal at maturity.
B36: Early-repay fee (gold-currency sink) | C36: 25 | D36: ingots | E36: Premium-currency cost to end a loan early. This is the hard-currency sink.
B37: Daily loan slots (free) | C37: 3 | D37: slots | E37: Free concurrent/sequential loans per day.
B38: Extra loan slot price | C38: 40 | D38: ingots | E38: Hard-currency cost to unlock an extra daily slot.
B39: Loan-feature adoption (share of DAU) | C39: 0.45 | D39: % | E39: Expected share of active players who use loans.
A41: E. MONETISATION VALUE ANCHORS
B42: Parameter | C42: Value | D42: Unit | E42: Notes / rationale
B43: Gold ingot retail value (USD) | C43: 0.01 | D43: $ / ingot | E43: Implied $ per premium currency unit from IAP bundles.
B44: Baseline ARPDAU | C44: 0.18 | D44: $ | E44: Current blended ARPDAU (ad+IAP), illustrative.

Sheet Baseline Economy
A2: BASELINE ECONOMY · CORE LOOP & THE CASH-SURPLUS PROBLEM
A3: Reconstructs the income vs. upgrade-cost curves and shows why late-game players accumulate cash with nothing to spend it on.
A4: Per-level progression (income vs. cost)
B5: Level | C5: Income/sec ($) | D5: Upgrade cost ($) | E5: Cumulative income/hr ($) | F5: Cost ÷ income-per-hr (hrs to afford) | G5: Cash buffer if no sink ($) | H5: Surplus ratio
B6: 1 | C6: =Parameters!$C$6*Parameters!$C$7^(B6-1) -> 50 | D6: =Parameters!$C$9*Parameters!$C$8^(B6-1) -> 100 | E6: =C6*3600 -> 180000 | F6: =D6/E6 -> 0.00055555556 | G6: =C6*3600*Parameters!$C$13 -> 2160000 | H6: =G6/D6 -> 21600
B7: 2 | C7: =Parameters!$C$6*Parameters!$C$7^(B7-1) -> 59 | D7: =Parameters!$C$9*Parameters!$C$8^(B7-1) -> 121 | E7: =C7*3600 -> 212400 | F7: =D7/E7 -> 0.00056967985 | G7: =C7*3600*Parameters!$C$13 -> 2548800 | H7: =G7/D7 -> 21064.463
B8: 3 | C8: =Parameters!$C$6*Parameters!$C$7^(B8-1) -> 69.62 | D8: =Parameters!$C$9*Parameters!$C$8^(B8-1) -> 146.41 | E8: =C8*3600 -> 250632 | F8: =D8/E8 -> 0.00058416324 | G8: =C8*3600*Parameters!$C$13 -> 3007584 | H8: =G8/D8 -> 20542.203
B9: 4 | C9: =Parameters!$C$6*Parameters!$C$7^(B9-1) -> 82.1516 | D9: =Parameters!$C$9*Parameters!$C$8^(B9-1) -> 177.1561 | E9: =C9*3600 -> 295745.76 | F9: =D9/E9 -> 0.00059901484 | G9: =C9*3600*Parameters!$C$13 -> 3548949.1 | H9: =G9/D9 -> 20032.893
B10: 5 | C10: =Parameters!$C$6*Parameters!$C$7^(B10-1) -> 96.938888 | D10: =Parameters!$C$9*Parameters!$C$8^(B10-1) -> 214.35888 | E10: =C10*3600 -> 348980 | F10: =D10/E10 -> 0.00061424403 | G10: =C10*3600*Parameters!$C$13 -> 4187760 | H10: =G10/D10 -> 19536.209
B11: 6 | C11: =Parameters!$C$6*Parameters!$C$7^(B11-1) -> 114.38789 | D11: =Parameters!$C$9*Parameters!$C$8^(B11-1) -> 259.37425 | E11: =C11*3600 -> 411796.4 | F11: =D11/E11 -> 0.00062986041 | G11: =C11*3600*Parameters!$C$13 -> 4941556.8 | H11: =G11/D11 -> 19051.84
B12: 7 | C12: =Parameters!$C$6*Parameters!$C$7^(B12-1) -> 134.97771 | D12: =Parameters!$C$9*Parameters!$C$8^(B12-1) -> 313.84284 | E12: =C12*3600 -> 485919.75 | F12: =D12/E12 -> 0.00064587381 | G12: =C12*3600*Parameters!$C$13 -> 5831037 | H12: =G12/D12 -> 18579.481
B13: 8 | C13: =Parameters!$C$6*Parameters!$C$7^(B13-1) -> 159.2737 | D13: =Parameters!$C$9*Parameters!$C$8^(B13-1) -> 379.74983 | E13: =C13*3600 -> 573385.3 | F13: =D13/E13 -> 0.00066229433 | G13: =C13*3600*Parameters!$C$13 -> 6880623.6 | H13: =G13/D13 -> 18118.832
B14: 9 | C14: =Parameters!$C$6*Parameters!$C$7^(B14-1) -> 187.94296 | D14: =Parameters!$C$9*Parameters!$C$8^(B14-1) -> 459.4973 | E14: =C14*3600 -> 676594.66 | F14: =D14/E14 -> 0.00067913232 | G14: =C14*3600*Parameters!$C$13 -> 8119135.9 | H14: =G14/D14 -> 17669.605
B15: 10 | C15: =Parameters!$C$6*Parameters!$C$7^(B15-1) -> 221.77269 | D15: =Parameters!$C$9*Parameters!$C$8^(B15-1) -> 555.99173 | E15: =C15*3600 -> 798381.69 | F15: =D15/E15 -> 0.0006963984 | G15: =C15*3600*Parameters!$C$13 -> 9580580.3 | H15: =G15/D15 -> 17231.516
B16: 11 | C16: =Parameters!$C$6*Parameters!$C$7^(B16-1) -> 261.69178 | D16: =Parameters!$C$9*Parameters!$C$8^(B16-1) -> 672.74999 | E16: =C16*3600 -> 942090.4 | F16: =D16/E16 -> 0.00071410344 | G16: =C16*3600*Parameters!$C$13 -> 11305085 | H16: =G16/D16 -> 16804.288
B17: 12 | C17: =Parameters!$C$6*Parameters!$C$7^(B17-1) -> 308.7963 | D17: =Parameters!$C$9*Parameters!$C$8^(B17-1) -> 814.02749 | E17: =C17*3600 -> 1111666.7 | F17: =D17/E17 -> 0.00073225861 | G17: =C17*3600*Parameters!$C$13 -> 13340000 | H17: =G17/D17 -> 16387.653
... B65: 60 | C65: =Parameters!$C$6*Parameters!$C$7^(B65-1) -> 870980.51 | D65: =Parameters!$C$9*Parameters!$C$8^(B65-1) -> 7661906.5 | E65: =C65*3600 -> 3.1355298e+09 | F65: =D65/E65 -> 0.0024435763 | G65: =C65*3600*Parameters!$C$13 -> 3.7626358e+10 | H65: =G65/D65 -> 4910.8349
A67: What the curve shows
B68: Early game | C68: ="At level 1, an upgrade costs "&TEXT(D6,"$#,##0")&" and is affordable in "&TEXT(F6,"0.0")&" hrs of income." -> At level 1, an upgrade costs $100 and is affordable in 0.0 hrs of income.
B69: Late game | C69: ="By level "&B65&", the offline cash buffer is "&TEXT(H65,"0.0")&"x the next upgrade cost — players sit on idle cash." -> By level 60, the offline cash buffer is 4910.8x the next upgrade cost — players sit on idle cash.
B70: The problem | C70: "Cost growth (1.21x) outpaces income growth (1.18x), yet the 12h offline cap lets cash pile up between the few upgrades that matter, and there is no compelling SINK to absorb it. That idle surplus is unused economic value and a missed monetisation touchpoint."

Sheet Loan Desk (A)
A2: OPTION A · THE LOAN DESK (soft-currency sink)
A3: Converts idle cash into a temporary income multiplier. Adds a real sink, a hard-currency touchpoint, and an active decision to the idle loop.
A4: Concept
B5: Players lock a share of their idle cash into a fixed-term 'loan'. While the loan runs, income/sec is boosted (the player is 'earning interest'). At maturity the principal returns plus a small soft bonus. Players may pay GOLD INGOTS to end a loan early (hard-currency sink) or to unlock extra loan slots. This drains the surplus the Baseline tab exposed, creates a meaningful choice (how much to lock, how long), and opens a non-ad monetisation lever, without pay-to-win, since rewards are time-based, not power-based.
A10: Worked example: representative mid-game player
B11: Input / step | C11: Value | D11: Unit | E11: Notes
B12: Player income/sec (illustrative, ~level 30) | C12: ='Baseline Economy'!C35 -> 6075.0271 | D12: $/sec | E12: Linked from Baseline tab (level 30 row).
B13: Idle cash balance (12h offline buffer) | C13: ='Baseline Economy'!G35 -> 2.6244117e+08 | D13: $ | E13: The surplus cash available to lock.
B14: Loan principal locked | C14: =C13*Parameters!$C$32 -> 1.0497647e+08 | D14: $ | E14: Idle cash x loan principal %.
B15: Loan term | C15: =Parameters!$C$33 -> 4 | D15: hours | E15: Cash locked for this long.
B16: Boosted income/sec while loan active | C16: =C12*Parameters!$C$34 -> 9112.5406 | D16: $/sec | E16: Income x multiplier during the term.
B17: Extra income earned over the term (vs. unboosted) | C17: =(C16-C12)*3600*C15 -> 43740195 | D17: $ | E17: The player's reward for committing cash.
B18: Soft interest bonus at maturity | C18: =C14*Parameters!$C$35 -> 10497647 | D18: $ | E18: Small bonus on principal returned.
B19: Total player benefit per loan | C19: =C17+C18 -> 54237842 | D19: $ | E19: Boost income + interest bonus.
B20: Boost reward as % of what 4h of normal play earns | C20: =C17/(C12*3600*C15) -> 0.5 | D20: % | E20: Cleaner than a stock-vs-flow yield: the boost reward equals this share of normal 4h earnings. Must stay modest so loans complement (not replace) active upgrading.
A22: Hard-currency sink sizing (across the player base)
B23: Metric | C23: Value | D23: Unit | E23: Notes
B24: DAU using the Loan Desk | C24: =Parameters!$C$17*Parameters!$C$39 -> 90000 | D24: users | E24: DAU x loan adoption %.
B25: Share who buy an early-repay or extra slot | C25: 0.08 | D25: % | E25: Assumed % of loan-users spending ingots (input).
B26: Ingots spent per spender per day | C26: =Parameters!$C$36 -> 25 | D26: ingots | E26: Avg ingot sink per spending user/day.
B27: Daily ingot sink (total) | C27: =C24*C25*C26 -> 180000 | D27: ingots | E27: Total premium currency drained per day.
B28: Implied daily $ value of ingot sink | C28: =C27*Parameters!$C$43 -> 1800 | D28: $ | E28: Ingot sink x retail ingot value.
B29: Incremental ARPDAU from Loan Desk | C29: =C28/Parameters!$C$17 -> 0.009 | D29: $ | E29: Daily ingot-sink value ÷ total DAU.
A31: Balance guardrails (anti-exploit / anti-inflation)
B32: • | C32: Principal capped at a % of CURRENT cash (Parameters D32), so it scales with the player and can't be gamed by hoarding.
B33: • | C33: Reward is a TIME-BASED income boost, not raw power, so it preserves prestige math and avoids pay-to-win.
B34: • | C34: Effective yield (C20) must stay BELOW what the same time spent actively upgrading would earn, or loans cannibalise core progression.
B35: • | C35: Early-repay costs HARD currency, so the only way to 'rush' is a sink, never a faucet.
B36: • | C36: Loan slots are limited (Parameters C37) so the feature can't dominate the session; extra slots are a paid sink.
B37: • | C37: Soft interest (Parameters C35) kept low so the Loan Desk drains cash on net rather than printing it.

Sheet Ad Tuning (B)
A2: OPTION B · REWARDED-AD REWARD TUNING
A3: Sizes the rewarded-video reward and estimates the ad-revenue / ARPDAU impact. Ads, not whales, carry this game's monetisation.
A4: Why this matters here
B5: AppQuantum estimates US IAP revenue-per-download at only ~$0.6 and notes much of the revenue comes from advertising, with 51% of users under 25 (low spend power). So the highest-leverage monetisation work is rewarded-ad DESIGN: making the reward feel worth watching, then optimising views/day and placement, not chasing IAP whales.
A9: Reward sizing: scale the reward to the player's own income
B10: Step | C10: Value | D10: Unit | E10: Notes
B11: Player income/sec (illustrative, ~level 30) | C11: ='Baseline Economy'!C35 -> 6075.0271 | D11: $/sec | E11: Linked from Baseline tab.
B12: Instant-reward = minutes of income granted | C12: 30 | D12: min | E12: Design lever: reward = N minutes of the player's own income (input).
B13: Instant-reward cash value | C13: =C11*60*C12 -> 10935049 | D13: $ | E13: Scales with player progress, so it stays meaningful all game.
B14: 2x boost duration per ad | C14: 2 | D14: hours | E14: Each ad doubles income for 2h, stackable to ~12h (input).
B15: Value of one 2x-boost ad | C15: =C11*3600*C14 -> 43740195 | D15: $ | E15: Extra cash from doubling income for the boost window.
A17: Ad-revenue impact (across the player base)
B18: Metric | C18: Baseline | D18: Tuned | E18: Notes
B19: Ad-watching DAU | C19: =Parameters!$C$17*Parameters!$C$19 -> 110000 | D19: =Parameters!$C$17*Parameters!$C$19 -> 110000 | E19: DAU x ad-watcher share (same population).
B20: Rewarded views per watcher/day | C20: =Parameters!$C$26 -> 6 | D20: =Parameters!$C$27 -> 8.5 | E20: Baseline vs. tuned views/day (Parameters C26/C27).
B21: Completed views per watcher/day | C21: =C20*Parameters!$C$28 -> 5.52 | D21: =D20*Parameters!$C$28 -> 7.82 | E21: x completion rate.
B22: Total completed rewarded views/day | C22: =C19*C21 -> 607200 | D22: =D19*D21 -> 860200 | E22: Watchers x completed views.
B23: Daily rewarded ad revenue | C23: =C22*Parameters!$C$24/1000 -> 9108 | D23: =D22*Parameters!$C$24/1000 -> 12903 | E23: Views x eCPM / 1000.
B24: Incremental rewarded ARPDAU | C24: =C23/Parameters!$C$17 -> 0.04554 | D24: =D23/Parameters!$C$17 -> 0.064515 | E24: Daily ad revenue ÷ total DAU.
B26: Revenue uplift from tuning | C26: =D23-C23 -> 3795 | E26: ="= +"&TEXT((D23-C23)/C23,"0.0%")&" daily rewarded ad revenue, same audience — purely from reward sizing + placement." -> = +41.7% daily rewarded ad revenue, same audience — purely from reward sizing + placement.
A28: Placement principle (free uplift, no extra ads)
B29: Sequence matters as much as frequency: industry tests show showing an interstitial AFTER a rewarded-video offer lifts ad ARPDAU ~+23% with no added frustration. Recommendation: keep rewarded ads opt-in and value-scaled (above), and A/B test interstitial sequencing at natural breakpoints (post-prestige, post-loan-maturity) rather than raising raw ad frequency.

Sheet KPI Impact
A2: KPI IMPACT · COMBINED LEVERS & SENSITIVITY
A3: Brings both features together into a monetisation view, with a sensitivity table and the A/B test plan.
A4: Combined incremental ARPDAU
B5: Lever | C5: Incr. ARPDAU | D5: Source
B6: Baseline ARPDAU | C6: =Parameters!$C$44 -> 0.18 | D6: Parameters C44 (current blended).
B7: + Loan Desk (Option A) | C7: ='Loan Desk (A)'!C29 -> 0.009 | D7: Hard-currency sink value ÷ DAU.
B8: + Ad tuning uplift (Option B) | C8: ='Ad Tuning (B)'!D24-'Ad Tuning (B)'!C24 -> 0.018975 | D8: Tuned minus baseline rewarded ARPDAU.
B9: Projected new ARPDAU | C9: =C6+C7+C8 -> 0.207975 | D9: ="= +"&TEXT((C7+C8)/C6,"0.0%")&" vs. baseline ARPDAU (illustrative)." -> = +15.5% vs. baseline ARPDAU (illustrative).
B11: Incremental daily revenue (all DAU) | C11: =(C7+C8)*Parameters!$C$17 -> 5595 | D11: Combined incremental ARPDAU x DAU.
B12: Incremental annual revenue (static DAU) | C12: =C11*365 -> 2042175 | D12: x 365 (illustrative, no growth).
A14: Sensitivity: Loan Desk daily $ sink. Adoption (rows) x ingot-spender share (cols)
B16: Adoption \ Spender% | C16: 0.04 | D16: 0.06 | E16: 0.08 | F16: 0.1 | G16: 0.12
B17: 0.25 | C17: =$C$23*$B17*C$16*Parameters!$C$36*Parameters!$C$43 -> 500 | D17: =$C$23*$B17*D$16*Parameters!$C$36*Parameters!$C$43 -> 750 | E17: =$C$23*$B17*E$16*Parameters!$C$36*Parameters!$C$43 -> 1000 | F17: =$C$23*$B17*F$16*Parameters!$C$36*Parameters!$C$43 -> 1250 | G17: =$C$23*$B17*G$16*Parameters!$C$36*Parameters!$C$43 -> 1500
B18: 0.35 | C18: =$C$23*$B18*C$16*Parameters!$C$36*Parameters!$C$43 -> 700 | D18: =$C$23*$B18*D$16*Parameters!$C$36*Parameters!$C$43 -> 1050 | E18: =$C$23*$B18*E$16*Parameters!$C$36*Parameters!$C$43 -> 1400 | F18: =$C$23*$B18*F$16*Parameters!$C$36*Parameters!$C$43 -> 1750 | G18: =$C$23*$B18*G$16*Parameters!$C$36*Parameters!$C$43 -> 2100
B19: 0.45 | C19: =$C$23*$B19*C$16*Parameters!$C$36*Parameters!$C$43 -> 900 | D19: =$C$23*$B19*D$16*Parameters!$C$36*Parameters!$C$43 -> 1350 | E19: =$C$23*$B19*E$16*Parameters!$C$36*Parameters!$C$43 -> 1800 | F19: =$C$23*$B19*F$16*Parameters!$C$36*Parameters!$C$43 -> 2250 | G19: =$C$23*$B19*G$16*Parameters!$C$36*Parameters!$C$43 -> 2700
B20: 0.55 | C20: =$C$23*$B20*C$16*Parameters!$C$36*Parameters!$C$43 -> 1100 | D20: =$C$23*$B20*D$16*Parameters!$C$36*Parameters!$C$43 -> 1650 | E20: =$C$23*$B20*E$16*Parameters!$C$36*Parameters!$C$43 -> 2200 | F20: =$C$23*$B20*F$16*Parameters!$C$36*Parameters!$C$43 -> 2750 | G20: =$C$23*$B20*G$16*Parameters!$C$36*Parameters!$C$43 -> 3300
B21: 0.65 | C21: =$C$23*$B21*C$16*Parameters!$C$36*Parameters!$C$43 -> 1300 | D21: =$C$23*$B21*D$16*Parameters!$C$36*Parameters!$C$43 -> 1950 | E21: =$C$23*$B21*E$16*Parameters!$C$36*Parameters!$C$43 -> 2600 | F21: =$C$23*$B21*F$16*Parameters!$C$36*Parameters!$C$43 -> 3250 | G21: =$C$23*$B21*G$16*Parameters!$C$36*Parameters!$C$43 -> 3900
B23: DAU anchor (from Parameters) | C23: =Parameters!$C$17 -> 200000
B25: Green cell = base-case assumption. Grid recalculates live from the Parameters tab (early-repay fee & ingot value).
A27: A/B test & rollout plan
B28: Hypothesis A (Loan Desk) | C28: Adding a soft-currency sink lifts D7 retention (more to do late-game) and ARPDAU (ingot sink) without hurting D1.
B29: Hypothesis B (Ad tuning) | C29: Scaling rewarded rewards to player income + resequencing interstitials lifts ad ARPDAU with neutral or positive retention.
B30: Design | C30: Assign at install (new players only). Split by platform (iOS vs Android behave differently). 4–5 variants of reward size / loan multiplier, not just on/off.
B31: Primary KPIs | C31: Evaluate retention (D1/D7) AND ARPU together; define the lever metric (loan adoption %, views/day). Require >=3% ARPDAU move before shipping.
B32: Guardrails | C32: Run the full 14-day retention window; never stack two tests on the same system; watch for currency inflation (cash balance distribution) and loan-yield cannibalising core upgrades.
B33: Ship / iterate / kill | C33: Ship if D7 up or flat AND ARPDAU +>=3%. Iterate if mixed. Kill if D1 drops or cash-sink causes progression complaints.

Sheet Sources
A2: SOURCES & ASSUMPTIONS
A3: What is sourced versus assumed. The model's value is the method; the numbers are adjustable.
A4: Key external data points (directional, third-party)
B5: Data point | C5: Source
B6: IBT revenue > $3.62M; > Idle Firefighter ($3.13M) | C6: AppQuantum deconstruction, Nov 2023 (Sensor Tower data)
B7: US IAP revenue-per-download ~ $0.6; ad-led monetisation | C7: AppQuantum, Nov 2023
B8: 51% of users male, under 25; D1 ~48% | C8: AppQuantum, Nov 2023
B9: 4th in niche downloads (Jul–Aug 2023), behind My Perfect Hotel | C9: AppQuantum, Nov 2023
B10: Industry IAP conversion 1.83% | C10: Unity Mobile Growth & Monetisation Report 2024
B11: Top 5% of players ≈ 48% of IAP revenue | C11: Moloco State of Mobile Gaming 2025
B12: Idle games ~73 rewarded videos per user (high tolerance) | C12: Appodeal Mobile Casual Benchmarks 2025
B13: Interstitial-after-rewarded lifts ad ARPDAU ~+23% | C13: Industry A/B test results (placement studies)
B14: Casual ~4 sessions/day, 5–6 min median, D1/D7 norms | C14: GameAnalytics Mobile Benchmarks 2024
B15: Idle math: cost exponential, prod linear, prestige sqrt | C15: A. Pecorella, 'The Math of Idle Games', GDC / Game Developer
B16: Currency stability / price rationality / proper allocation | C16: Machinations Manifesto (w/ E. Castronova), GDC 2023
B17: IBT mechanics: departments, managers, prestige, offline cap | C17: Kolibri Games Help Center; Level Winner & GamingonPhone guides
A19: Modelling assumptions (clearly NOT Kolibri's internal data)
B20: Assumption | C20: Why this value / how to refine
B21: Income growth 1.18x, cost growth 1.21x per level | C21: Idle norm (Pecorella). Cost>income so progress self-throttles. Refine via APK data-mine or in-game logging.
B22: Base income 50/sec, base cost $100 | C22: Anchors for early-game feel; tune to actual onboarding telemetry.
B23: DAU 200,000 | C23: Illustrative scaling figure; replace with real DAU.
B24: Loan principal 40% of cash, 4h term, 1.5x boost | C24: Tuned so yield stays below active-upgrade returns (anti-cannibalisation). A/B test the real values.
B25: Loan adoption 45%; 8% of users buy a sink | C25: Mid-range engagement-feature assumptions; validate live.
B26: Rewarded eCPM $15; views 6 -> 8.5/day after tuning | C26: Blended eCPM; uplift from reward sizing + placement, not more ads.
B27: Ingot retail value $0.01 | C27: Back-solved from typical IAP bundle pricing; set from real store data.
B29: Every number here lives on the Parameters tab and is labelled as an assumption. Swapping in Kolibri's real telemetry would make the model production-grade without changing its structure.
